aerich/__init__.py
aerich/__main__.py
aerich/_compat.py
aerich/cli.py
aerich/coder.py
aerich/ddl/__init__.py
aerich/ddl/mysql/__init__.py
aerich/ddl/postgres/__init__.py
aerich/ddl/sqlite/__init__.py
aerich/enums.py
aerich/exceptions.py
aerich/inspectdb/__init__.py
aerich/inspectdb/mysql.py
aerich/inspectdb/postgres.py
aerich/inspectdb/sqlite.py
aerich/migrate.py
aerich/models.py
aerich/utils.py
aerich/version.py
aerich-0.9.0.dist-info/LICENSE
aerich-0.9.0.dist-info/METADATA
aerich-0.9.0.dist-info/WHEEL
aerich-0.9.0.dist-info/entry_points.txt
aerich-0.9.0.dist-info/RECORD
