Metadata-Version: 2.3
Name: aerich
Version: 0.9.0
Summary: A database migrations tool for Tortoise ORM.
License: Apache-2.0
Keywords: migrate,Tortoise-ORM,mysql
Author: long2ice
Author-email: long2ice@gmail.com>
Requires-Python: >=3.9
Classifier: License :: OSI Approved :: Apache Software License
Classifier: Programming Language :: Python :: 3
Classifier: Programming Language :: Python :: 3.9
Classifier: Programming Language :: Python :: 3.10
Classifier: Programming Language :: Python :: 3.11
Classifier: Programming Language :: Python :: 3.12
Classifier: Programming Language :: Python :: 3.13
Provides-Extra: asyncmy
Provides-Extra: asyncpg
Provides-Extra: mysql
Provides-Extra: psycopg
Provides-Extra: toml
Requires-Dist: aiomysql (>=0.2.0) ; extra == "mysql"
Requires-Dist: asyncclick (>=8.1.7,<9.0.0)
Requires-Dist: asyncmy (>=0.2.9) ; (python_version < "4.0") and (extra == "asyncmy")
Requires-Dist: asyncpg ; extra == "asyncpg"
Requires-Dist: dictdiffer (>=0.9.0,<1.0.0)
Requires-Dist: eval-type-backport (>=0.2.2,<1.0.0) ; python_version < "3.10"
Requires-Dist: psycopg[binary,pool] (>=3.0.12,<4.0.0) ; extra == "psycopg"
Requires-Dist: pydantic (>=2.0.2,!=2.1.0,!=2.7.0,<3.0.0)
Requires-Dist: tomli-w (>=1.1.0,<2.0.0) ; (python_version >= "3.11") and (extra == "toml")
Requires-Dist: tomlkit (>=0.11.4,<1.0.0) ; (python_version < "3.11") and (extra == "toml")
Requires-Dist: tortoise-orm (>=0.24.0,<1.0.0)
Project-URL: Documentation, https://github.com/tortoise/aerich
Project-URL: Homepage, https://github.com/tortoise/aerich
Project-URL: Repository, https://github.com/tortoise/aerich.git
